{"images":[{"startdate":"20230318","fullstartdate":"202303180700","enddate":"20230319","url":"/th?id=OHR.MarsTars_EN-US7511744420_1920x1080.jpg&rf=LaDigue_1920x1080.jpg&pid=hp","urlbase":"/th?id=OHR.MarsTars_EN-US7511744420","copyright":"Gamboa Crater, Mars (© NASA/JPL-Caltech/University of Arizona)","copyrightlink":"https://www.bing.com/search?q=mars&form=hpcapt&filters=HpDate%3a%2220230318_0700%22","title":"Out of this world","quiz":"/search?q=Bing+homepage+quiz&filters=WQOskey:%22HPQuiz_20230318_MarsTars%22&FORM=HPQUIZ","wp":true,"hsh":"9a34cbae93d8f20572c71cccfa95d126","drk":1,"top":1,"bot":1,"hs":[]}],"tooltips":{"loading":"Loading...","previous":"Previous image","next":"Next image","walle":"This image is not available to download as wallpaper.","walls":"Download this image. Use of this image is restricted to wallpaper only."}}