{"images":[{"startdate":"20250821","fullstartdate":"202508210700","enddate":"20250822","url":"/th?id=OHR.WheatearBird_EN-US2132045619_1920x1080.jpg&rf=LaDigue_1920x1080.jpg&pid=hp","urlbase":"/th?id=OHR.WheatearBird_EN-US2132045619","copyright":"Wheatear and flowering heather, Peak District National Park, England (© Ben Hall/Nature Picture Library)","copyrightlink":"https://www.bing.com/search?q=Wheatear+bird&form=hpcapt&filters=HpDate%3a%2220250821_0700%22","title":"Perched and poised","quiz":"/search?q=Bing+homepage+quiz&filters=WQOskey:%22HPQuiz_20250821_WheatearBird%22&FORM=HPQUIZ","wp":true,"hsh":"d213b27649fc629927f639a6dee7f949","drk":1,"top":1,"bot":1,"hs":[]}],"tooltips":{"loading":"Loading...","previous":"Previous image","next":"Next image","walle":"This image is not available to download as wallpaper.","walls":"Download this image. Use of this image is restricted to wallpaper only."}}